nkia_ai_dependency/__init__.py
nkia_ai_dependency-1.0.4.dist-info/METADATA
nkia_ai_dependency-1.0.4.dist-info/WHEEL
nkia_ai_dependency-1.0.4.dist-info/RECORD
