Metadata-Version: 2.1
Name: nkia-ai-dependency
Version: 1.0.4
Summary: NKIA AI Shared Dependency
Author: hjyang
Author-email: hjyang@nkia.co.kr
Requires-Python: >=3.10,<4.0
Classifier: Programming Language :: Python :: 3
Classifier: Programming Language :: Python :: 3.10
Classifier: Programming Language :: Python :: 3.11
Classifier: Programming Language :: Python :: 3.12
Provides-Extra: all
Provides-Extra: deploy
Provides-Extra: loganomaly
Provides-Extra: metricanomaly
Provides-Extra: processrca
Provides-Extra: staticthreshold
Provides-Extra: threcommender
Requires-Dist: aiohttp (==3.9.3) ; extra == "deploy" or extra == "all"
Requires-Dist: cassandra-driver (==3.29.0) ; extra == "deploy" or extra == "all"
Requires-Dist: datefinder (==0.7.3) ; extra == "loganomaly" or extra == "all"
Requires-Dist: elasticsearch (==7.15.1) ; extra == "deploy" or extra == "loganomaly" or extra == "all"
Requires-Dist: fastapi (==0.109.2) ; extra == "deploy" or extra == "all"
Requires-Dist: gunicorn (==21.2.0) ; extra == "deploy" or extra == "all"
Requires-Dist: httpx (==0.25.2) ; extra == "deploy" or extra == "all"
Requires-Dist: more-itertools (==10.2.0) ; extra == "metricanomaly" or extra == "threcommender" or extra == "staticthreshold" or extra == "loganomaly" or extra == "all"
Requires-Dist: networkx (==3.1) ; extra == "processrca" or extra == "all"
Requires-Dist: numpy (==1.26.4) ; extra == "metricanomaly" or extra == "processrca" or extra == "threcommender" or extra == "staticthreshold" or extra == "deploy" or extra == "loganomaly" or extra == "all"
Requires-Dist: pandas (==2.2.2) ; extra == "metricanomaly" or extra == "processrca" or extra == "threcommender" or extra == "staticthreshold" or extra == "deploy" or extra == "loganomaly" or extra == "all"
Requires-Dist: pydantic (==2.11.4) ; extra == "deploy" or extra == "all"
Requires-Dist: pygrok (==1.0.0) ; extra == "loganomaly" or extra == "all"
Requires-Dist: pymongo (==4.12.1) ; extra == "deploy" or extra == "all"
Requires-Dist: pytest (==8.3.2) ; extra == "metricanomaly" or extra == "processrca" or extra == "threcommender" or extra == "staticthreshold" or extra == "deploy" or extra == "loganomaly" or extra == "all"
Requires-Dist: python-dateutil (==2.9.0) ; extra == "loganomaly" or extra == "all"
Requires-Dist: python-dotenv (==1.0.1) ; extra == "deploy" or extra == "loganomaly" or extra == "all"
Requires-Dist: pytimekr (==0.1.0) ; extra == "metricanomaly" or extra == "all"
Requires-Dist: pytz (==2024.1) ; extra == "metricanomaly" or extra == "loganomaly" or extra == "all"
Requires-Dist: redis (==3.5.3) ; extra == "deploy" or extra == "loganomaly" or extra == "all"
Requires-Dist: redis-py-cluster (==2.1.3) ; extra == "deploy" or extra == "all"
Requires-Dist: requests (==2.32.2) ; extra == "all"
Requires-Dist: scikit-learn (==1.3.2) ; extra == "metricanomaly" or extra == "processrca" or extra == "loganomaly" or extra == "all"
Requires-Dist: scipy (==1.13.0) ; extra == "metricanomaly" or extra == "processrca" or extra == "threcommender" or extra == "loganomaly" or extra == "all"
Requires-Dist: seaborn (==0.13.2) ; extra == "threcommender" or extra == "all"
Requires-Dist: statsmodels (==0.14.1) ; extra == "metricanomaly" or extra == "processrca" or extra == "loganomaly" or extra == "all"
Requires-Dist: uvicorn (==0.27.1) ; extra == "deploy" or extra == "all"
